qcSim/__init__.py
qcSim/operator.py
qcSim/operators.py
qcSim/state.py
qcSim-0.1.1.dist-info/LICENCE.txt
qcSim-0.1.1.dist-info/METADATA
qcSim-0.1.1.dist-info/WHEEL
qcSim-0.1.1.dist-info/top_level.txt
qcSim-0.1.1.dist-info/RECORD
