Metadata-Version: 2.1
Name: qcSim
Version: 0.1.1
Summary: A python package for the simulation of quantum computers.
Home-page: UNKNOWN
Author: Yannis Fleischhauer
Author-email: yannis.fleischhauer@wiwi.uni-kl.de
License: UNKNOWN
Platform: UNKNOWN
Classifier: Programming Language :: Python :: 3
Classifier: License :: OSI Approved :: MIT License
Classifier: Operating System :: OS Independent
